treat_sim/__init__.py
treat_sim/datasets.py
treat_sim/distributions.py
treat_sim/model.py
treat_sim/data/ed_arrivals.csv
treat_sim/data/ed_arrivals_scenario1.csv
treat_sim-2.2.0.dist-info/METADATA
treat_sim-2.2.0.dist-info/WHEEL
treat_sim-2.2.0.dist-info/licenses/LICENSE
treat_sim-2.2.0.dist-info/RECORD
