Metadata-Version: 2.3
Name: treat-sim
Version: 2.2.0
Summary: A Python Free and Open Source Software implementation of the Treatment Centre Model from Nelson (2013)
Project-URL: Homepage, https://github.com/pythonhealthdatascience/stars-treat-sim
Project-URL: Bug Tracker, https://github.com/pythonhealthdatascience/stars-treat-sim
Project-URL: Documentation, https://pythonhealthdatascience.github.io/stars-simpy-example-docs/
Author-email: Thomas Monks <forecast-tools@gmail.com>
License-Expression: MIT
License-File: LICENSE
Classifier: License :: OSI Approved :: MIT License
Classifier: Operating System :: OS Independent
Classifier: Programming Language :: Python :: 3.8
Classifier: Programming Language :: Python :: 3.9
Classifier: Programming Language :: Python :: 3.10
Classifier: Programming Language :: Python :: 3.11
Classifier: Programming Language :: Python :: 3.12
Requires-Python: >=3.8.19
Requires-Dist: matplotlib>=3.3.4
Requires-Dist: numpy>=1.19.2
Requires-Dist: pandas>=1.2.3
Requires-Dist: scipy>=1.6.1
Requires-Dist: simpy>=4.0.1
